hashbeaf/__init__.py
hashbeaf/hashbeaf.py
hashbeaf/utils.py
hashbeaf/words.py
hashbeaf-1.1.1.dist-info/LICENSE
hashbeaf-1.1.1.dist-info/METADATA
hashbeaf-1.1.1.dist-info/WHEEL
hashbeaf-1.1.1.dist-info/entry_points.txt
hashbeaf-1.1.1.dist-info/top_level.txt
hashbeaf-1.1.1.dist-info/RECORD
