Metadata-Version: 2.1
Name: hashbeaf
Version: 1.1.1
Summary: A simple utility to create user-specified git commit hashes
Author-email: Cedric Nugteren <web@cedricnugteren.nl>
Project-URL: Homepage, https://github.com/cnugteren/hashbeaf
Project-URL: Bug Tracker, https://github.com/cnugteren/hashbeaf/issues
Classifier: Programming Language :: Python :: 3
Classifier: License :: OSI Approved :: MIT License
Classifier: Operating System :: OS Independent
Requires-Python: >=3.7
License-File: LICENSE
